{
  "attributes": [
    {
      "default": "nil",
      "size": null,
      "type": "bigint",
      "source": "id",
      "references": null,
      "allow_nil?": false,
      "generated?": true,
      "primary_key?": true
    },
    {
      "default": "nil",
      "size": null,
      "type": "text",
      "source": "name",
      "references": null,
      "allow_nil?": false,
      "generated?": false,
      "primary_key?": false
    },
    {
      "default": "nil",
      "size": null,
      "type": "text",
      "source": "description",
      "references": null,
      "allow_nil?": true,
      "generated?": false,
      "primary_key?": false
    },
    {
      "default": "[]",
      "size": null,
      "type": [
        "array",
        [
          "array",
          "text"
        ]
      ],
      "source": "models",
      "references": null,
      "allow_nil?": false,
      "generated?": false,
      "primary_key?": false
    },
    {
      "default": "nil",
      "size": null,
      "type": "text",
      "source": "slug",
      "references": null,
      "allow_nil?": true,
      "generated?": false,
      "primary_key?": false
    },
    {
      "default": "nil",
      "size": null,
      "type": "utc_datetime_usec",
      "source": "inserted_at",
      "references": null,
      "allow_nil?": false,
      "generated?": false,
      "primary_key?": false
    },
    {
      "default": "nil",
      "size": null,
      "type": "utc_datetime_usec",
      "source": "updated_at",
      "references": null,
      "allow_nil?": false,
      "generated?": false,
      "primary_key?": false
    },
    {
      "default": "nil",
      "size": null,
      "type": "bigint",
      "source": "user_id",
      "references": {
        "name": "networks_user_id_fkey",
        "table": "users",
        "on_delete": null,
        "multitenancy": {
          "global": null,
          "attribute": null,
          "strategy": null
        },
        "primary_key?": true,
        "destination_attribute": "id",
        "deferrable": false,
        "destination_attribute_default": null,
        "destination_attribute_generated": null,
        "on_update": null
      },
      "allow_nil?": false,
      "generated?": false,
      "primary_key?": false
    }
  ],
  "table": "networks",
  "hash": "7A4BAA4EE0A346F49281754B4915928F1AEA14363CECD2A55BBDBFEC19DCA9EA",
  "repo": "Elixir.Panic.Repo",
  "identities": [],
  "multitenancy": {
    "global": null,
    "attribute": null,
    "strategy": null
  },
  "base_filter": null,
  "custom_indexes": [],
  "custom_statements": [],
  "has_create_action": true
}